Metadata-Version: 1.0
Name: standards
Version: 0.0.1
Summary: Standards
Home-page: UNKNOWN
Author: Bülent Aldemir
Author-email: buelent@e-evolution.de
License: MIT
Platform: UNKNOWN
